{"is_source_file": true, "format": "TypeScript", "description": "This file is an ESLint configuration script for a Vue.js project, setting up linting rules, plugin integrations, and file ignore patterns.", "external_files": ["eslint-plugin-vue", "@vue/eslint-config-typescript", "@vitest/eslint-plugin", "@vue/eslint-config-prettier"], "external_methods": ["defineConfigWithVueTs", "vueTsConfigs", "pluginVue.configs", "pluginVitest.configs"], "published": ["default"], "classes": [], "methods": [{"name": "defineConfigWithVueTs", "description": "Defines the ESLint configuration with Vue and TypeScript support."}], "calls": ["defineConfigWithVueTs", "pluginVue.configs['flat/essential']", "vueTsConfigs.recommended", "pluginVitest.configs.recommended", "skipFormatting"], "search-terms": ["eslint", "vue", "typescript", "eslint-config", "eslint-plugin-vue", "vitest", "prettier", "eslint ignore patterns", "configuration", "eslint setup"], "state": 2, "file_id": 3, "knowledge_revision": 37, "git_revision": "506a645eac86e334d183fe96c587aaf592ab1c3b", "ctags": [], "hash": "e25c340ceed14d09bdaf1f13a69b34bc", "format-version": 4, "code-base-name": "frontend_app", "filename": "frontend_app/eslint.config.ts", "revision_history": [{"37": "506a645eac86e334d183fe96c587aaf592ab1c3b"}]}